{"cameraMode":{"drawMode":0,"name":"Shaded","section":"Shading Mode"},"sceneLighting":true,"audioPlay":false,"sceneViewState":{"m_AlwaysRefresh":false,"showFog":true,"showSkybox":true,"showFlares":true,"showImageEffects":true,"showParticleSystems":true,"showVisualEffectGraphs":true,"m_FxEnabled":true},"in2DMode":false,"pivot":{"x":-13.40999984741211,"y":1.5199999809265137,"z":-34.439998626708987},"rotation":{"x":0.16210147738456727,"y":-0.758791983127594,"z":0.2061200588941574,"w":0.5963315963745117},"size":10.0,"orthographic":false}